setup.py
qcloud_cos/__init__.py
qcloud_cos/cos_auth.py
qcloud_cos/cos_client.py
qcloud_cos/cos_config.py
qcloud_cos/cos_cred.py
qcloud_cos/cos_err.py
qcloud_cos/cos_op.py
qcloud_cos/cos_params_check.py
qcloud_cos/cos_request.py
qcloud_cos.egg-info/PKG-INFO
qcloud_cos.egg-info/SOURCES.txt
qcloud_cos.egg-info/dependency_links.txt
qcloud_cos.egg-info/requires.txt
qcloud_cos.egg-info/top_level.txt