Metadata-Version: 1.0
Name: qcloud-cos
Version: 3.3.2
Summary: python sdk for tencent qcloud cos
Home-page: UNKNOWN
Author: chengwu
Author-email: chengwu@tencent.com
License: MIT License
Platform: UNKNOWN
